salve_dependency_hub/__init__.py
salve_dependency_hub/languages/__init__.py
salve_dependency_hub/languages/arduino.py
salve_dependency_hub/languages/bash.py
salve_dependency_hub/languages/c.py
salve_dependency_hub/languages/c_sharp.py
salve_dependency_hub/languages/commonlisp.py
salve_dependency_hub/languages/cpp.py
salve_dependency_hub/languages/css.py
salve_dependency_hub/languages/cuda.py
salve_dependency_hub/languages/embedded_template.py
salve_dependency_hub/languages/glsl.py
salve_dependency_hub/languages/go.py
salve_dependency_hub/languages/gstlaunch.py
salve_dependency_hub/languages/html.py
salve_dependency_hub/languages/java.py
salve_dependency_hub/languages/javascript.py
salve_dependency_hub/languages/jsdoc.py
salve_dependency_hub/languages/json.py
salve_dependency_hub/languages/odin.py
salve_dependency_hub/languages/php.py
salve_dependency_hub/languages/pymanifest.py
salve_dependency_hub/languages/python.py
salve_dependency_hub/languages/ruby.py
salve_dependency_hub/languages/rust.py
salve_dependency_hub/languages/scss.py
salve_dependency_hub/languages/slang.py
salve_dependency_hub/languages/starlark.py
salve_dependency_hub/languages/toml.py
salve_dependency_hub/languages/typescript.py
salve_dependency_hub/languages/wgsl_bevy.py
salve_dependency_hub/languages/yaml.py
salve_dependency_hub-1.0.2.dist-info/LICENSE
salve_dependency_hub-1.0.2.dist-info/METADATA
salve_dependency_hub-1.0.2.dist-info/WHEEL
salve_dependency_hub-1.0.2.dist-info/top_level.txt
salve_dependency_hub-1.0.2.dist-info/RECORD
